quickcall_supertrace/__init__.py
quickcall_supertrace/main.py
quickcall_supertrace/db/__init__.py
quickcall_supertrace/db/client.py
quickcall_supertrace/db/schema.py
quickcall_supertrace/hooks/__init__.py
quickcall_supertrace/hooks/cli.py
quickcall_supertrace/hooks/handlers.py
quickcall_supertrace/hooks/models.py
quickcall_supertrace/hooks/setup.py
quickcall_supertrace/hooks/statusline.py
quickcall_supertrace/ingest/__init__.py
quickcall_supertrace/ingest/importer.py
quickcall_supertrace/ingest/parser.py
quickcall_supertrace/ingest/poller.py
quickcall_supertrace/ingest/scanner.py
quickcall_supertrace/metrics/__init__.py
quickcall_supertrace/metrics/chart_metrics.py
quickcall_supertrace/metrics/interaction_metrics.py
quickcall_supertrace/metrics/preprocess.py
quickcall_supertrace/metrics/registry.py
quickcall_supertrace/metrics/timing_metrics.py
quickcall_supertrace/metrics/token_metrics.py
quickcall_supertrace/metrics/tool_metrics.py
quickcall_supertrace/metrics/work_metrics.py
quickcall_supertrace/routes/__init__.py
quickcall_supertrace/routes/ingest.py
quickcall_supertrace/routes/intents.py
quickcall_supertrace/routes/media.py
quickcall_supertrace/routes/metrics.py
quickcall_supertrace/routes/sessions.py
quickcall_supertrace/routes/version.py
quickcall_supertrace/services/__init__.py
quickcall_supertrace/services/version.py
quickcall_supertrace/static/favicon-96x96.png
quickcall_supertrace/static/favicon.ico
quickcall_supertrace/static/favicon.svg
quickcall_supertrace/static/index.html
quickcall_supertrace/static/assets/exportTemplate-C3b6WG4q.js
quickcall_supertrace/static/assets/index-B3w_787x.js
quickcall_supertrace/static/assets/index-BD3_VbQx.css
quickcall_supertrace/static/assets/remixicon-C6oSHjyR.woff
quickcall_supertrace/static/assets/remixicon-Cj6uv-K3.svg
quickcall_supertrace/static/assets/remixicon-Cr1pveRX.ttf
quickcall_supertrace/static/assets/remixicon-DMdG15mt.woff2
quickcall_supertrace/static/assets/remixicon-Dj-GCdWP.eot
quickcall_supertrace-0.2.13.dist-info/METADATA
quickcall_supertrace-0.2.13.dist-info/WHEEL
quickcall_supertrace-0.2.13.dist-info/entry_points.txt
quickcall_supertrace-0.2.13.dist-info/RECORD
