Metadata-Version: 2.4
Name: quickcall-supertrace
Version: 0.2.13
Summary: QuickCall SuperTrace - Tracing server for AI coding assistant sessions
Project-URL: Homepage, https://quickcall.dev
Project-URL: Repository, https://github.com/quickcall-dev/quickcall-supertrace
Project-URL: Documentation, https://github.com/quickcall-dev/quickcall-supertrace#readme
Project-URL: Issues, https://github.com/quickcall-dev/quickcall-supertrace/issues
Author: Sagar Sarkale
License-Expression: Apache-2.0
Keywords: ai,claude,coding-assistant,llm,monitoring,observability,tracing
Classifier: Development Status :: 4 - Beta
Classifier: Framework :: FastAPI
Classifier: Intended Audience :: Developers
Classifier: License :: OSI Approved :: Apache Software License
Classifier: Programming Language :: Python :: 3
Classifier: Programming Language :: Python :: 3.10
Classifier: Programming Language :: Python :: 3.11
Classifier: Programming Language :: Python :: 3.12
Classifier: Topic :: Software Development :: Debuggers
Classifier: Topic :: System :: Monitoring
Requires-Python: >=3.10
Requires-Dist: aiosqlite>=0.20.0
Requires-Dist: fastapi>=0.115.0
Requires-Dist: pydantic>=2.0.0
Requires-Dist: uvicorn[standard]>=0.32.0
